Avance1/Mux/probador_mux.v
`timescale 1ns/100ps
module probar(clk, reset_L, data_in_0, data_in_1, valid_in_0, valid_in_1, valid_out, data_out);
	output reg [7:0]data_in_0;
	output reg [7:0]data_in_1;
	output reg valid_in_0;
	output reg valid_in_1;
	output reg clk;
	output reg reset_L;
	input wire valid_out;
	input wire [7:0]data_out; 

	initial clk<=0;	

	always #2 clk <= ~clk;

	initial begin
		repeat (1) begin
		@(posedge clk);
			data_in_0<=8'b0;
			data_in_1<=8'b0;
			valid_in_0<=0;
			valid_in_0<=0;
			reset_L<=0;
		end
        repeat (1) begin
		@(posedge clk);
			data_in_0<=8'hAA;
			data_in_1<=8'hBB;
			valid_in_0<=0;
			valid_in_1<=0;
			reset_L<=1;
		end
		 repeat (1) begin
		@(posedge clk);
			data_in_0<=8'hAC;
			data_in_1<=8'hBC;
			valid_in_0<=1;
			valid_in_1<=0;
			reset_L<=1;
		end
		repeat (1) begin
		@(posedge clk);
			data_in_0<=8'hFF;
			data_in_1<=8'hDC;
			valid_in_0<=1;
			valid_in_1<=1;
			reset_L<=1;
		end
		repeat (1) begin
		@(posedge clk);
			data_in_0<=8'hEE;
			data_in_1<=8'h00;
			valid_in_0<=1;
			valid_in_1<=1;
			reset_L<=1;
		end
		repeat (1) begin
		@(posedge clk);
			data_in_0<=8'hDD;
			data_in_1<=8'h01;
			valid_in_0<=1;
			valid_in_1<=1;
			reset_L<=1;
		end
		repeat (1) begin
		@(posedge clk);
			data_in_0<=8'hCC;
			data_in_1<=8'h02;
			valid_in_0<=0;
			valid_in_1<=0;
			reset_L<=1;
		end
		repeat (1) begin
		@(posedge clk);
			data_in_0<=8'hCD;
			data_in_1<=8'hEF;
			valid_in_0<=0;
			valid_in_1<=0;
			reset_L<=1;
        end
        repeat (1) begin
		@(posedge clk);
			data_in_0<=8'hFE;
			data_in_1<=8'hDC;
			valid_in_0<=0;
			valid_in_1<=1;
			reset_L<=1;
        end
        repeat (1) begin
		@(posedge clk);
			data_in_0<=8'hBD;
			data_in_1<=8'h03;
			valid_in_0<=1;
			valid_in_1<=1;
			reset_L<=1;
        end
        repeat (1) begin
		@(posedge clk);
			data_in_0<=8'hBB;
			data_in_1<=8'h04;
			valid_in_0<=0;
			valid_in_1<=0;
			reset_L<=1;
        end
        repeat (1) begin
		@(posedge clk);
			data_in_0<=8'hEF;
			data_in_1<=8'h24;
			valid_in_0<=0;
			valid_in_1<=0;
			reset_L<=1;
        end
        repeat (1) begin
		@(posedge clk);
			data_in_0<=8'hCE;
			data_in_1<=8'h33;
			valid_in_0<=1;
			valid_in_1<=1;
			reset_L<=1;
        end 
        repeat (1) begin
            data_in_0<=8'hAA;
			data_in_1<=8'h05;
			valid_in_0<=1;
			valid_in_1<=1;
			reset_L<=1;
        end
        repeat (1) begin
        @(posedge clk);
			data_in_0<=8'h09;
			data_in_1<=8'h06;
			valid_in_0<=0;
			valid_in_1<=0;
			reset_L<=1;
        end
        repeat (1) begin
        @(posedge clk);
			data_in_0<=8'hBF;
			data_in_1<=8'h43;
			valid_in_0<=0;
			valid_in_1<=0;
			reset_L<=1;
        end
        repeat (1) begin
		@(posedge clk);
			data_in_0<=8'hCA;
			data_in_1<=8'h56;
			valid_in_0<=1;
			valid_in_1<=1;
			reset_L<=1;
        end 
        repeat (1) begin
            data_in_0<=8'h88;
			data_in_1<=8'h07;
			valid_in_0<=1;
			valid_in_1<=1;
			reset_L<=1;
        end
        repeat (1) begin
        @(posedge clk);
			data_in_0<=8'h77;
			data_in_1<=8'h08;
			valid_in_0<=0;
			valid_in_1<=0;
			reset_L<=1;
        end
        repeat (1) begin
        @(posedge clk);
			data_in_0<=8'b0;
			data_in_1<=8'b0;
			valid_in_0<=0;
			valid_in_1<=0;
			reset_L<=1;
        end
        repeat (1) begin
            data_in_0<=8'b0;
			data_in_1<=8'b0;
			valid_in_0<=0;
			valid_in_1<=0;
			reset_L<=0;
        end
		#60 $finish;
	end
endmodule

Avance1/Mux/cmos_cells.v
module BUF(A, Y);
input A;
output Y;
assign Y = A;
endmodule

module NOT(A, Y);
input A;
output Y;

assign #5 Y = ~A;

endmodule

module NAND(A, B, Y);
input A, B;
output Y;
assign #5.9 Y = ~(A & B);
endmodule

module NOR(A, B, Y);
input A, B;
output Y;
assign #5.5 Y = ~(A | B);
endmodule

module DFF(C, D, Q);
input C, D;
output reg Q;
always @(posedge C)
    #5
	Q <= D;
endmodule

module DFFSR(C, D, Q, S, R);
input C, D, S, R;
output reg Q;
always @(posedge C, posedge S, posedge R)
	if (S)
		Q <= 1'b1;
	else if (R)
		Q <= 1'b0;
	else
		Q <= D;
endmodule

Avance1/Mux/synth_mux.v
/* Generated by Yosys 0.8 (git sha1 5706e90) */

(* top =  1  *)
(* src = "mux.v:2" *)
module mux_synth(clk, reset_L, data_in_0, data_in_1, valid_in_0, valid_in_1, valid_out, data_out);
  (* src = "mux.v:17" *)
  wire [7:0] _000_;
  (* src = "mux.v:17" *)
  wire _001_;
  (* src = "mux.v:17" *)
  wire _002_;
  (* src = "mux.v:17" *)
  wire _003_;
  (* src = "mux.v:17" *)
  wire _004_;
  wire _005_;
  wire _006_;
  wire _007_;
  wire _008_;
  wire _009_;
  wire _010_;
  wire _011_;
  wire _012_;
  wire _013_;
  wire _014_;
  wire _015_;
  wire _016_;
  wire _017_;
  wire _018_;
  wire _019_;
  wire _020_;
  wire _021_;
  wire _022_;
  wire _023_;
  wire _024_;
  wire _025_;
  wire _026_;
  wire _027_;
  wire _028_;
  wire _029_;
  wire _030_;
  wire _031_;
  wire _032_;
  wire _033_;
  wire _034_;
  wire _035_;
  wire _036_;
  wire _037_;
  wire _038_;
  wire _039_;
  wire _040_;
  wire _041_;
  wire _042_;
  wire _043_;
  wire _044_;
  wire _045_;
  wire _046_;
  wire _047_;
  wire _048_;
  wire _049_;
  wire _050_;
  wire _051_;
  wire _052_;
  wire _053_;
  wire _054_;
  wire _055_;
  wire _056_;
  wire _057_;
  wire _058_;
  wire _059_;
  wire _060_;
  (* src = "mux.v:3" *)
  input clk;
  (* src = "mux.v:5" *)
  input [7:0] data_in_0;
  (* src = "mux.v:6" *)
  input [7:0] data_in_1;
  (* src = "mux.v:10" *)
  output [7:0] data_out;
  (* src = "mux.v:4" *)
  input reset_L;
  (* src = "mux.v:13" *)
  wire selector;
  (* src = "mux.v:14" *)
  wire v_activo_0;
  (* src = "mux.v:15" *)
  wire v_activo_1;
  (* src = "mux.v:7" *)
  input valid_in_0;
  (* src = "mux.v:8" *)
  input valid_in_1;
  (* src = "mux.v:9" *)
  output valid_out;
  NOT _061_ (
    .A(valid_in_0),
    .Y(_007_)
  );
  NOT _062_ (
    .A(valid_in_1),
    .Y(_008_)
  );
  NOT _063_ (
    .A(v_activo_0),
    .Y(_009_)
  );
  NOT _064_ (
    .A(v_activo_1),
    .Y(_010_)
  );
  NOT _065_ (
    .A(reset_L),
    .Y(_011_)
  );
  NOT _066_ (
    .A(selector),
    .Y(_012_)
  );
  NOR _067_ (
    .A(v_activo_0),
    .B(v_activo_1),
    .Y(_013_)
  );
  NOR _068_ (
    .A(_011_),
    .B(_013_),
    .Y(_004_)
  );
  NOR _069_ (
    .A(v_activo_1),
    .B(reset_L),
    .Y(_014_)
  );
  NOR _070_ (
    .A(_007_),
    .B(v_activo_1),
    .Y(_015_)
  );
  NOR _071_ (
    .A(_008_),
    .B(v_activo_0),
    .Y(_016_)
  );
  NAND _072_ (
    .A(valid_in_1),
    .B(_009_),
    .Y(_017_)
  );
  NOR _073_ (
    .A(_015_),
    .B(_017_),
    .Y(_018_)
  );
  NOR _074_ (
    .A(_012_),
    .B(_017_),
    .Y(_019_)
  );
  NAND _075_ (
    .A(selector),
    .B(_016_),
    .Y(_020_)
  );
  NOR _076_ (
    .A(_011_),
    .B(_019_),
    .Y(_021_)
  );
  NAND _077_ (
    .A(reset_L),
    .B(_020_),
    .Y(_022_)
  );
  NOR _078_ (
    .A(_018_),
    .B(_022_),
    .Y(_023_)
  );
  NOR _079_ (
    .A(_014_),
    .B(_023_),
    .Y(_003_)
  );
  NAND _080_ (
    .A(_015_),
    .B(_021_),
    .Y(_024_)
  );
  NAND _081_ (
    .A(v_activo_0),
    .B(_011_),
    .Y(_025_)
  );
  NAND _082_ (
    .A(_024_),
    .B(_025_),
    .Y(_002_)
  );
  NAND _083_ (
    .A(_015_),
    .B(_016_),
    .Y(_026_)
  );
  NAND _084_ (
    .A(_015_),
    .B(_019_),
    .Y(_027_)
  );
  NAND _085_ (
    .A(_012_),
    .B(_026_),
    .Y(_028_)
  );
  NAND _086_ (
    .A(_027_),
    .B(_028_),
    .Y(_029_)
  );
  NOR _087_ (
    .A(_011_),
    .B(_029_),
    .Y(_001_)
  );
  NOR _088_ (
    .A(v_activo_0),
    .B(_010_),
    .Y(_030_)
  );
  NAND _089_ (
    .A(data_in_1[0]),
    .B(_030_),
    .Y(_031_)
  );
  NAND _090_ (
    .A(v_activo_0),
    .B(data_in_0[0]),
    .Y(_032_)
  );
  NAND _091_ (
    .A(_031_),
    .B(_032_),
    .Y(_033_)
  );
  NAND _092_ (
    .A(reset_L),
    .B(_033_),
    .Y(_034_)
  );
  NOT _093_ (
    .A(_034_),
    .Y(_000_[0])
  );
  NAND _094_ (
    .A(data_in_1[1]),
    .B(_030_),
    .Y(_035_)
  );
  NAND _095_ (
    .A(v_activo_0),
    .B(data_in_0[1]),
    .Y(_036_)
  );
  NAND _096_ (
    .A(_035_),
    .B(_036_),
    .Y(_037_)
  );
  NAND _097_ (
    .A(reset_L),
    .B(_037_),
    .Y(_038_)
  );
  NOT _098_ (
    .A(_038_),
    .Y(_000_[1])
  );
  NAND _099_ (
    .A(data_in_1[2]),
    .B(_030_),
    .Y(_039_)
  );
  NAND _100_ (
    .A(v_activo_0),
    .B(data_in_0[2]),
    .Y(_040_)
  );
  NAND _101_ (
    .A(_039_),
    .B(_040_),
    .Y(_041_)
  );
  NAND _102_ (
    .A(reset_L),
    .B(_041_),
    .Y(_042_)
  );
  NOT _103_ (
    .A(_042_),
    .Y(_000_[2])
  );
  NAND _104_ (
    .A(data_in_1[3]),
    .B(_030_),
    .Y(_043_)
  );
  NAND _105_ (
    .A(v_activo_0),
    .B(data_in_0[3]),
    .Y(_044_)
  );
  NAND _106_ (
    .A(_043_),
    .B(_044_),
    .Y(_045_)
  );
  NAND _107_ (
    .A(reset_L),
    .B(_045_),
    .Y(_046_)
  );
  NOT _108_ (
    .A(_046_),
    .Y(_000_[3])
  );
  NAND _109_ (
    .A(data_in_1[4]),
    .B(_030_),
    .Y(_047_)
  );
  NAND _110_ (
    .A(v_activo_0),
    .B(data_in_0[4]),
    .Y(_048_)
  );
  NAND _111_ (
    .A(_047_),
    .B(_048_),
    .Y(_049_)
  );
  NAND _112_ (
    .A(reset_L),
    .B(_049_),
    .Y(_050_)
  );
  NOT _113_ (
    .A(_050_),
    .Y(_000_[4])
  );
  NAND _114_ (
    .A(data_in_1[5]),
    .B(_030_),
    .Y(_051_)
  );
  NAND _115_ (
    .A(v_activo_0),
    .B(data_in_0[5]),
    .Y(_052_)
  );
  NAND _116_ (
    .A(_051_),
    .B(_052_),
    .Y(_053_)
  );
  NAND _117_ (
    .A(reset_L),
    .B(_053_),
    .Y(_054_)
  );
  NOT _118_ (
    .A(_054_),
    .Y(_000_[5])
  );
  NAND _119_ (
    .A(data_in_1[6]),
    .B(_030_),
    .Y(_055_)
  );
  NAND _120_ (
    .A(v_activo_0),
    .B(data_in_0[6]),
    .Y(_056_)
  );
  NAND _121_ (
    .A(_055_),
    .B(_056_),
    .Y(_057_)
  );
  NAND _122_ (
    .A(reset_L),
    .B(_057_),
    .Y(_058_)
  );
  NOT _123_ (
    .A(_058_),
    .Y(_000_[6])
  );
  NAND _124_ (
    .A(data_in_1[7]),
    .B(_030_),
    .Y(_059_)
  );
  NAND _125_ (
    .A(v_activo_0),
    .B(data_in_0[7]),
    .Y(_060_)
  );
  NAND _126_ (
    .A(_059_),
    .B(_060_),
    .Y(_005_)
  );
  NAND _127_ (
    .A(reset_L),
    .B(_005_),
    .Y(_006_)
  );
  NOT _128_ (
    .A(_006_),
    .Y(_000_[7])
  );
  (* src = "mux.v:17" *)
  DFF _129_ (
    .C(clk),
    .D(_004_),
    .Q(valid_out)
  );
  (* src = "mux.v:17" *)
  DFF _130_ (
    .C(clk),
    .D(_000_[0]),
    .Q(data_out[0])
  );
  (* src = "mux.v:17" *)
  DFF _131_ (
    .C(clk),
    .D(_000_[1]),
    .Q(data_out[1])
  );
  (* src = "mux.v:17" *)
  DFF _132_ (
    .C(clk),
    .D(_000_[2]),
    .Q(data_out[2])
  );
  (* src = "mux.v:17" *)
  DFF _133_ (
    .C(clk),
    .D(_000_[3]),
    .Q(data_out[3])
  );
  (* src = "mux.v:17" *)
  DFF _134_ (
    .C(clk),
    .D(_000_[4]),
    .Q(data_out[4])
  );
  (* src = "mux.v:17" *)
  DFF _135_ (
    .C(clk),
    .D(_000_[5]),
    .Q(data_out[5])
  );
  (* src = "mux.v:17" *)
  DFF _136_ (
    .C(clk),
    .D(_000_[6]),
    .Q(data_out[6])
  );
  (* src = "mux.v:17" *)
  DFF _137_ (
    .C(clk),
    .D(_000_[7]),
    .Q(data_out[7])
  );
  (* src = "mux.v:17" *)
  DFF _138_ (
    .C(clk),
    .D(_001_),
    .Q(selector)
  );
  (* src = "mux.v:17" *)
  DFF _139_ (
    .C(clk),
    .D(_002_),
    .Q(v_activo_0)
  );
  (* src = "mux.v:17" *)
  DFF _140_ (
    .C(clk),
    .D(_003_),
    .Q(v_activo_1)
  );
endmodule

Avance1/Mux/mux.v
`timescale 1ns/100ps
module mux (
            input            clk,
            input            reset_L,
            input [7:0]      data_in_0,
            input [7:0]      data_in_1,
            input            valid_in_0,
            input            valid_in_1,
            output reg valid_out,
            output reg [7:0] data_out
            );

         reg selector;
         reg v_activo_0;
         reg v_activo_1;
            
   always @ (posedge clk) begin
        if (!reset_L) begin
            data_out <= 0;
            valid_out <= 0;
            selector <= 0;
        end 
        else begin
            if (valid_in_0 && valid_in_1 && ~v_activo_0 && ~v_activo_1) begin
                selector <= ~selector;
                v_activo_1 <= selector;
                v_activo_0 <= ~selector;
            end
            else begin
                if (valid_in_0 && ~v_activo_1) begin
                    v_activo_0 <= 1;
                end else begin
                    v_activo_0 <= 0;
                end 
                if (valid_in_1 && ~v_activo_0) begin
                    v_activo_1 <= 1;
                end else begin
                    v_activo_1 <= 0;
                end 
            end
            
            valid_out = v_activo_0 || v_activo_1;
            
            if (v_activo_0) begin
                data_out <= data_in_0;
            end else if (v_activo_1) begin
                data_out <= data_in_1;
                end else begin
                data_out <= 0;
                end
        end
    end
endmodule

Avance1/Mux/t_b_mux.v
`timescale 1ns/100ps
`include "cmos_cells.v"
`include "synth_mux.v"
module tb();
	wire clk;
	wire reset_L;
	wire [7:0]data_in_0;
	wire [7:0]data_in_1;
	wire valid_in_0;
	wire valid_in_1;
	wire valid_out;
	wire [7:0] data_out;
	mux mx(clk, reset_L, data_in_0, data_in_1, valid_in_0, valid_in_1, valid_out, data_out);
	mux_synth MXsynth(clk, reset_L, data_in_0, data_in_1, valid_in_0, valid_in_1, valid_out, data_out);
	probar	proba(clk, reset_L, data_in_0, data_in_1, valid_in_0, valid_in_1, valid_out, data_out);	
	
	initial

		begin
		$dumpfile("mux.vcd");
		$dumpvars;
			$display("clk reset_L data_in_0 data_in_1 valid_in_0 valid_in_1 valid_out data_out");
			$monitor("%b %b %b %b %b %b %b %b", clk, reset_L, data_in_0, data_in_1, valid_in_0, valid_in_1, valid_out, data_out);

		end

endmodule

Avance1/Mux/mux.vcd
$date
	Wed Jun 12 08:52:55 2019
$end
$version
	Icarus Verilog
$end
$timescale
	100ps
$end
$scope module tb $end
$var wire 1 ! valid_out $end
$var wire 1 " valid_in_1 $end
$var wire 1 # valid_in_0 $end
$var wire 1 $ reset_L $end
$var wire 8 % data_out [7:0] $end
$var wire 8 & data_in_1 [7:0] $end
$var wire 8 ' data_in_0 [7:0] $end
$var wire 1 ( clk $end
$scope module mx $end
$var wire 1 " valid_in_1 $end
$var wire 1 # valid_in_0 $end
$var wire 1 $ reset_L $end
$var wire 8 ) data_in_1 [7:0] $end
$var wire 8 * data_in_0 [7:0] $end
$var wire 1 ( clk $end
$var reg 8 + data_out [7:0] $end
$var reg 1 , selector $end
$var reg 1 - v_activo_0 $end
$var reg 1 . v_activo_1 $end
$var reg 1 ! valid_out $end
$upscope $end
$scope module proba $end
$var wire 8 / data_out [7:0] $end
$var wire 1 ! valid_out $end
$var reg 1 ( clk $end
$var reg 8 0 data_in_0 [7:0] $end
$var reg 8 1 data_in_1 [7:0] $end
$var reg 1 $ reset_L $end
$var reg 1 # valid_in_0 $end
$var reg 1 " valid_in_1 $end
$upscope $end
$upscope $end
$enddefinitions $end
#0
$dumpvars
bx 1
bx 0
bx /
x.
x-
x,
bx +
bx *
bx )
0(
bx '
bx &
bx %
x$
x#
x"
x!
$end
#20
b0 %
b0 +
b0 /
0.
0-
0$
0#
b0 &
b0 )
b0 1
b0 '
b0 *
b0 0
1(
#40
0(
#60
1$
0"
b10111011 &
b10111011 )
b10111011 1
b10101010 '
b10101010 *
b10101010 0
0,
0!
1(
#80
0(
#100
1#
b10111100 &
b10111100 )
b10111100 1
b10101100 '
b10101100 *
b10101100 0
1(
#120
0(
#140
1"
b11011100 &
b11011100 )
b11011100 1
b11111111 '
b11111111 *
b11111111 0
1-
1(
#160
0(
#180
b11111111 %
b11111111 +
b11111111 /
b0 &
b0 )
b0 1
b11101110 '
b11101110 *
b11101110 0
1!
1(
#200
0(
#220
b1 &
b1 )
b1 1
b11011101 '
b11011101 *
b11011101 0
b11101110 %
b11101110 +
b11101110 /
1(
#240
0(
#260
b11011101 %
b11011101 +
b11011101 /
0"
0#
b10 &
b10 )
b10 1
b11001100 '
b11001100 *
b11001100 0
1(
#280
0(
#300
b11101111 &
b11101111 )
b11101111 1
b11001101 '
b11001101 *
b11001101 0
b11001100 %
b11001100 +
b11001100 /
0-
1(
#320
0(
#340
b0 %
b0 +
b0 /
1"
b11011100 &
b11011100 )
b11011100 1
b11111110 '
b11111110 *
b11111110 0
0!
1(
#360
0(
#380
1#
b11 &
b11 )
b11 1
b10111101 '
b10111101 *
b10111101 0
1.
1(
#400
0(
#420
b11 %
b11 +
b11 /
0"
0#
b100 &
b100 )
b100 1
b10111011 '
b10111011 *
b10111011 0
1!
1(
#440
0(
#460
b100100 &
b100100 )
b100100 1
b11101111 '
b11101111 *
b11101111 0
b100 %
b100 +
b100 /
0.
1(
#480
0(
#500
b0 %
b0 +
b0 /
1"
1#
b101 &
b101 )
b101 1
b10101010 '
b10101010 *
b10101010 0
0!
1(
#520
0(
#540
0"
0#
b110 &
b110 )
b110 1
b1001 '
b1001 *
b1001 0
1-
1,
1(
#560
0(
#580
b1001 %
b1001 +
b1001 /
0-
b1000011 &
b1000011 )
b1000011 1
b10111111 '
b10111111 *
b10111111 0
1!
1(
#600
0(
#620
1"
1#
b111 &
b111 )
b111 1
b10001000 '
b10001000 *
b10001000 0
b0 %
b0 +
b0 /
0!
1(
#640
0(
#660
1.
0,
0"
0#
b1000 &
b1000 )
b1000 1
b1110111 '
b1110111 *
b1110111 0
1(
#680
0(
#700
0$
b0 &
b0 )
b0 1
b0 '
b0 *
b0 0
b1000 %
b1000 +
b1000 /
0.
1!
1(
#720
0(
#740
0!
b0 %
b0 +
b0 /
1(
